demandlib/__init__.py
demandlib/config.py
demandlib/demandlib.ini
demandlib/particular_profiles.py
demandlib/tools.py
demandlib/bdew/__init__.py
demandlib/bdew/_profiles25.py
demandlib/bdew/elec_slp.py
demandlib/bdew/heat_building.py
demandlib/bdew/bdew_data/g25.csv
demandlib/bdew/bdew_data/h25.csv
demandlib/bdew/bdew_data/l25.csv
demandlib/bdew/bdew_data/p25.csv
demandlib/bdew/bdew_data/s25.csv
demandlib/bdew/bdew_data/selp_series.csv
demandlib/bdew/bdew_data/shlp_hour_factors.csv
demandlib/bdew/bdew_data/shlp_sigmoid_factors.csv
demandlib/bdew/bdew_data/shlp_weekday_factors.csv
demandlib/vdi/__init__.py
demandlib/vdi/dwd_try.py
demandlib/vdi/regions.py
demandlib/vdi/resources_weather/TRY2010_01_Jahr.dat
demandlib/vdi/resources_weather/TRY2010_02_Jahr.dat
demandlib/vdi/resources_weather/TRY2010_03_Jahr.dat
demandlib/vdi/resources_weather/TRY2010_04_Jahr.dat
demandlib/vdi/resources_weather/TRY2010_05_Jahr.dat
demandlib/vdi/resources_weather/TRY2010_06_Jahr.dat
demandlib/vdi/resources_weather/TRY2010_07_Jahr.dat
demandlib/vdi/resources_weather/TRY2010_08_Jahr.dat
demandlib/vdi/resources_weather/TRY2010_09_Jahr.dat
demandlib/vdi/resources_weather/TRY2010_10_Jahr.dat
demandlib/vdi/resources_weather/TRY2010_11_Jahr.dat
demandlib/vdi/resources_weather/TRY2010_12_Jahr.dat
demandlib/vdi/resources_weather/TRY2010_13_Jahr.dat
demandlib/vdi/resources_weather/TRY2010_14_Jahr.dat
demandlib/vdi/resources_weather/TRY2010_15_Jahr.dat
demandlib/vdi/resources_weather/TRY_polygons.geojson
demandlib/vdi/vdi_data/VDI_4655_Typtag-Faktoren.csv
demandlib/vdi/vdi_data/VDI_4655_Typtage.csv
demandlib-0.2.2.dist-info/licenses/LICENSE
demandlib-0.2.2.dist-info/WHEEL
demandlib-0.2.2.dist-info/METADATA
demandlib-0.2.2.dist-info/RECORD
