Metadata-Version: 2.4
Name: demandlib
Version: 0.2.2
Summary: Creating heat and power demand profiles from annual values
Author-email: oemof developer group <contact@oemof.org>
Requires-Python: >=3.10
Classifier: Development Status :: 5 - Production/Stable
Classifier: Intended Audience :: Developers
Classifier: Intended Audience :: Science/Research
Classifier: License :: OSI Approved :: MIT License
Classifier: Operating System :: Unix
Classifier: Operating System :: POSIX
Classifier: Operating System :: Microsoft :: Windows
Classifier: Operating System :: MacOS
Classifier: Operating System :: OS Independent
Classifier: Programming Language :: Python
Classifier: Programming Language :: Python :: 3
Classifier: Programming Language :: Python :: 3.9
Classifier: Programming Language :: Python :: 3.10
Classifier: Programming Language :: Python :: 3.11
Classifier: Programming Language :: Python :: Implementation :: CPython
Classifier: Topic :: Utilities
License-File: LICENSE
Requires-Dist: numpy >= 2.0
Requires-Dist: pandas >= 2.0
Requires-Dist: build ; extra == "build"
Requires-Dist: check-manifest ; extra == "build"
Requires-Dist: flake8 ; extra == "build"
Requires-Dist: flit ; extra == "build"
Requires-Dist: isort ; extra == "build"
Requires-Dist: pygments ; extra == "build"
Requires-Dist: readme-renderer ; extra == "build"
Requires-Dist: twine ; extra == "build"
Requires-Dist: sphinx ; extra == "docs"
Requires-Dist: sphinx_rtd_theme ; extra == "docs"
Requires-Dist: matplotlib ; extra == "examples"
Requires-Dist: workalendar ; extra == "examples"
Requires-Dist: shapely >= 2.0.0 ; extra == "geometry"
Requires-Dist: geopandas ; extra == "geometry"
Requires-Dist: coverage ; extra == "test"
Requires-Dist: matplotlib ; extra == "test"
Requires-Dist: pytest ; extra == "test"
Requires-Dist: geopandas ; extra == "test"
Requires-Dist: tox ; extra == "tox"
Project-URL: Changelog, https://demandlib.readthedocs.io/en/latest/changelog.html
Project-URL: Documentation, https://demandlib.readthedocs.io/
Project-URL: Homepage, https://github.com/oemof/demandlib
Project-URL: Issue Tracker, https://github.com/oemof/demandlib/issues/
Provides-Extra: build
Provides-Extra: docs
Provides-Extra: examples
Provides-Extra: geometry
Provides-Extra: test
Provides-Extra: tox
